Metadata-Version: 2.1
Name: amogus
Version: 0.1
Summary: AMOGUS
Home-page: http://github.com/dmitrijkotov634/amogus
Author: Dmitry Kotov
Author-email: dmitrijkotov634@gmail.com
License: MIT
Platform: UNKNOWN
